terminal_image/__init__.py
terminal_image/cli.py
terminal_image-0.1.0.dist-info/licenses/LICENSE.txt
terminal_image-0.1.0.dist-info/METADATA
terminal_image-0.1.0.dist-info/WHEEL
terminal_image-0.1.0.dist-info/entry_points.txt
terminal_image-0.1.0.dist-info/top_level.txt
terminal_image-0.1.0.dist-info/RECORD
