Metadata-Version: 2.4
Name: terminal-image
Version: 0.1.0
Summary: Display images in the terminal using ANSI colors
Author-email: Soundhearddev <letdes50@gmail.com>
License-Expression: Apache-2.0
Requires-Python: >=3.7
License-File: LICENSE.txt
Requires-Dist: opencv-python>=4.0.0
Dynamic: license-file
